saigon/__init__.py
saigon/fflags.py
saigon/interface.py
saigon/iter.py
saigon/logutils.py
saigon/model.py
saigon/sftp.py
saigon/utils.py
saigon/aws/__init__.py
saigon/aws/cognito.py
saigon/aws/rest.py
saigon/aws/s3.py
saigon/aws/secrets.py
saigon/aws/ssm.py
saigon/aws/flow/__init__.py
saigon/aws/flow/rest.py
saigon/aws/flow/s3.py
saigon/aws/flow/sqs.py
saigon/fastapi/__init__.py
saigon/fastapi/handlers.py
saigon/fastapi/headers.py
saigon/fastapi/utils.py
saigon/orm/__init__.py
saigon/orm/config.py
saigon/orm/connection.py
saigon/orm/model.py
saigon/rest/__init__.py
saigon/rest/client.py
saigon_test/.flake8
saigon_test/__init__.py
saigon_test/fixtures.py
saigon_test/infra.py
saigon_test/lint.py
saigon_test/cli/__init__.py
saigon_test/cli/cognito.py
saigon_test/cli/shell/__init__.py
saigon_test/cli/shell/handlers.py
saigon_test/cli/shell/shell.py
saigon_py-0.13.1.dist-info/METADATA
saigon_py-0.13.1.dist-info/WHEEL
saigon_py-0.13.1.dist-info/entry_points.txt
saigon_py-0.13.1.dist-info/RECORD
